src/__init__.py
src/__main__.py
src/cli/__init__.py
src/cli/__main__.py
src/npyc/__init__.py
src/npyc/__main__.py
src/utils/__init__.py
src/utils/__main__.py
src/utils/console.py
nupython-0.0.1.dist-info/METADATA
nupython-0.0.1.dist-info/WHEEL
nupython-0.0.1.dist-info/entry_points.txt
nupython-0.0.1.dist-info/top_level.txt
nupython-0.0.1.dist-info/RECORD
